TheSilentPyPi/TheSilent.py
TheSilentPyPi/__init__.py
TheSilentPyPi/gpu.py
TheSilentPyPi-0.0.205.dist-info/METADATA
TheSilentPyPi-0.0.205.dist-info/WHEEL
TheSilentPyPi-0.0.205.dist-info/top_level.txt
TheSilentPyPi-0.0.205.dist-info/RECORD
