Metadata-Version: 2.1
Name: TheSilentPyPi
Version: 0.0.205
Summary: Python penetration testing, osint, and digital forensics multi tool!
Author-email: Michael Mueller <michael.j.mueller.pro@gmail.com>
Project-URL: Homepage, https://github.com/Invizabel/The-Silent-PyPi
Project-URL: Bug Tracker, https://github.com/Invizabel/The-Silent-PyPi/issues
Classifier: Programming Language :: Python :: 3
Classifier: License :: OSI Approved :: MIT License
Classifier: Operating System :: OS Independent
Requires-Python: >=3.7
Requires-Dist: numpy
Requires-Dist: pillow
Requires-Dist: requests
Requires-Dist: urllib3
